udchinese/__init__.py
udchinese/ud-chinese.udpipe
udchinese/udchinese.py
udchinese/spacy/__init__.py
udchinese/spacy/udchinese2spacy.py
udchinese-0.6.1.dist-info/LICENSE.txt
udchinese-0.6.1.dist-info/METADATA
udchinese-0.6.1.dist-info/WHEEL
udchinese-0.6.1.dist-info/top_level.txt
udchinese-0.6.1.dist-info/RECORD
