Metadata-Version: 2.1
Name: udchinese
Version: 0.6.1
Summary: Tokenizer POS-tagger and Dependency-parser for Chinese (简体/繁體/文言文)
Home-page: https://github.com/KoichiYasuoka/UD-Chinese
Author: Koichi Yasuoka
Author-email: yasuoka@kanji.zinbun.kyoto-u.ac.jp
License: MIT
Project-URL: Source, https://github.com/KoichiYasuoka/UD-Chinese
Project-URL: Tracker, https://github.com/KoichiYasuoka/UD-Chinese/issues
Keywords: udpipe nlp
Platform: UNKNOWN
Classifier: License :: OSI Approved :: MIT License
Classifier: Programming Language :: Python :: 3
Classifier: Operating System :: OS Independent
Classifier: Topic :: Text Processing :: Linguistic
Classifier: Natural Language :: Chinese (Simplified)
Classifier: Natural Language :: Chinese (Traditional)
Requires-Python: >=3.6
Requires-Dist: udkanbun (>=3.3.7)
